LICENSE
MANIFEST.in
README.rst
setup.py
btc_floating_windows.egg-info/PKG-INFO
btc_floating_windows.egg-info/SOURCES.txt
btc_floating_windows.egg-info/dependency_links.txt
btc_floating_windows.egg-info/top_level.txt
floating_windows/__init__.py
floating_windows/apps.py
floating_windows/static/floating_windows/css/tray.css
floating_windows/static/floating_windows/css/windows.css
floating_windows/static/floating_windows/img/bars.svg
floating_windows/static/floating_windows/img/check-mark.svg
floating_windows/static/floating_windows/img/circle.svg
floating_windows/static/floating_windows/img/dots.svg
floating_windows/static/floating_windows/img/error-gears.svg
floating_windows/static/floating_windows/img/error.svg
floating_windows/static/floating_windows/img/grid.svg
floating_windows/static/floating_windows/img/robot.svg
floating_windows/static/floating_windows/js/ajax.js
floating_windows/static/floating_windows/js/tray.js
floating_windows/static/floating_windows/js/windows.js
floating_windows/templates/floating_windows/tray.html
floating_windows/templates/floating_windows/windows/default.html
floating_windows/templates/floating_windows/windows/default_body.html