Metadata-Version: 1.1
Name: btc-floating-windows
Version: 1.0
Summary: Floating windows for use as pop-ups, modal or separate sources of information in a user graphical interface.
Home-page: https://github.com/MEADez/btc-floating-windows
Author: MEADez
Author-email: m3adez@gmail.com
License: BSD License
Platform: UNKNOWN
Classifier: Environment :: Web Environment
Classifier: Framework :: Django
Classifier: Intended Audience :: Developers
Classifier: License :: OSI Approved :: BSD License
Classifier: Operating System :: OS Independent
Classifier: Programming Language :: Python :: 3.6
Classifier: Topic :: Internet :: WWW/HTTP
Classifier: Topic :: Internet :: WWW/HTTP :: Dynamic Content
